{
  "student": {
    "name": "Dimas Cahyo Margono"
  },
  "lecturerCode": "DSS",
  "courses": [
    {
      "courseCode": "SE101",
      "courseName": "Pemrograman Dasar",
      "lecturerName": "Danang Sadewo"
    },
    {
      "courseCode": "SE102",
      "courseName": "Struktur Data",
      "lecturerName": "Danang Sadewo"
    },
    {
      "courseCode": "SE103",
      "courseName": "Pemrograman Berorientasi Objek",
      "lecturerName": "Danang Sadewo"

    },
    {
      "courseCode": "SE104",
      "courseName": "Basis Data",
      "lecturerName": "Danang Sadewo"
    },
    {
      "courseCode": "SE105",
      "courseName": "Praktikum Jaringan Komputer",
      "lecturerName": "Danang Sadewo"
    }
  ]
}